flask_ldap_auth.py
flask_ldap_auth-0.3.dist-info/LICENSE
flask_ldap_auth-0.3.dist-info/METADATA
flask_ldap_auth-0.3.dist-info/WHEEL
flask_ldap_auth-0.3.dist-info/top_level.txt
flask_ldap_auth-0.3.dist-info/RECORD
